{"nodes": [{"id": "Mathlib.LinearAlgebra.Alternating.Basic", "short_name": "Basic", "kind": "theorem", "module": "Mathlib.LinearAlgebra.Alternating.Basic", "namespace": "Mathlib.LinearAlgebra.Alternating", "doc_string": null, "source_range": null, "deps": ["Mathlib.Topology.Algebra.Module.Alternating.Basic", "Mathlib.LinearAlgebra.ExteriorAlgebra.Basic", "Mathlib.LinearAlgebra.Alternating.DomCoprod", "Mathlib.LinearAlgebra.Matrix.Determinant"], "used_by_count": 3}, {"id": "Mathlib.LinearAlgebra.Alternating.DomCoprod", "short_name": "DomCoprod", "kind": "theorem", "module": "Mathlib.LinearAlgebra.Alternating.DomCoprod", "namespace": "Mathlib.LinearAlgebra.Alternating", "doc_string": null, "source_range": null, "deps": [], "used_by_count": 2}]}