{"nodes": [{"id": "Mathlib.CategoryTheory.Localization.Construction", "short_name": "Construction", "kind": "theorem", "module": "Mathlib.CategoryTheory.Localization.Construction", "namespace": "Mathlib.CategoryTheory.Localization", "doc_string": null, "source_range": null, "deps": ["Mathlib.CategoryTheory.Localization.Predicate"], "used_by_count": 2}, {"id": "Mathlib.CategoryTheory.Localization.Predicate", "short_name": "Predicate", "kind": "theorem", "module": "Mathlib.CategoryTheory.Localization.Predicate", "namespace": "Mathlib.CategoryTheory.Localization", "doc_string": null, "source_range": null, "deps": ["Mathlib.CategoryTheory.Shift.Localization", "Mathlib.CategoryTheory.Localization.Opposite", "Mathlib.CategoryTheory.Localization.Adjunction", "Mathlib.CategoryTheory.Localization.Equivalence"], "used_by_count": 1}, {"id": "Mathlib.CategoryTheory.Localization.Opposite", "short_name": "Opposite", "kind": "theorem", "module": "Mathlib.CategoryTheory.Localization.Opposite", "namespace": "Mathlib.CategoryTheory.Localization", "doc_string": null, "source_range": null, "deps": ["Mathlib.CategoryTheory.Localization.CalculusOfFractions"], "used_by_count": 1}, {"id": "Mathlib.CategoryTheory.Localization.Adjunction", "short_name": "Adjunction", "kind": "theorem", "module": "Mathlib.CategoryTheory.Localization.Adjunction", "namespace": "Mathlib.CategoryTheory.Localization", "doc_string": null, "source_range": null, "deps": [], "used_by_count": 2}, {"id": "Mathlib.CategoryTheory.Localization.Equivalence", "short_name": "Equivalence", "kind": "theorem", "module": "Mathlib.CategoryTheory.Localization.Equivalence", "namespace": "Mathlib.CategoryTheory.Localization", "doc_string": null, "source_range": null, "deps": ["Mathlib.CategoryTheory.Localization.Prod", "Mathlib.CategoryTheory.Localization.LocalizerMorphism"], "used_by_count": 2}, {"id": "Mathlib.CategoryTheory.Localization.CalculusOfFractions", "short_name": "CalculusOfFractions", "kind": "theorem", "module": "Mathlib.CategoryTheory.Localization.CalculusOfFractions", "namespace": "Mathlib.CategoryTheory.Localization", "doc_string": null, "source_range": null, "deps": [], "used_by_count": 1}, {"id": "Mathlib.CategoryTheory.Localization.Prod", "short_name": "Prod", "kind": "theorem", "module": "Mathlib.CategoryTheory.Localization.Prod", "namespace": "Mathlib.CategoryTheory.Localization", "doc_string": null, "source_range": null, "deps": [], "used_by_count": 1}, {"id": "Mathlib.CategoryTheory.Localization.LocalizerMorphism", "short_name": "LocalizerMorphism", "kind": "theorem", "module": "Mathlib.CategoryTheory.Localization.LocalizerMorphism", "namespace": "Mathlib.CategoryTheory.Localization", "doc_string": null, "source_range": null, "deps": ["Mathlib.CategoryTheory.Localization.Composition"], "used_by_count": 1}, {"id": "Mathlib.CategoryTheory.Localization.Composition", "short_name": "Composition", "kind": "theorem", "module": "Mathlib.CategoryTheory.Localization.Composition", "namespace": "Mathlib.CategoryTheory.Localization", "doc_string": null, "source_range": null, "deps": [], "used_by_count": 1}]}