{"nodes": [{"id": "Mathlib.Algebra.Module.Basic", "short_name": "Basic", "kind": "theorem", "module": "Mathlib.Algebra.Module.Basic", "namespace": "Mathlib.Algebra.Module", "doc_string": null, "source_range": null, "deps": ["Mathlib.Topology.Support", "Mathlib.Dynamics.BirkhoffSum.Average", "Mathlib.RepresentationTheory.Basic", "Mathlib.CategoryTheory.Preadditive.Basic", "Mathlib.GroupTheory.FreeAbelianGroup", "Mathlib.GroupTheory.GroupAction.SubMulAction", "Mathlib.GroupTheory.GroupAction.Hom", "Mathlib.GroupTheory.Subgroup.Basic", "Mathlib.RingTheory.Subsemiring.Basic", "Mathlib.Combinatorics.Pigeonhole", "Mathlib.Combinatorics.SimpleGraph.Regularity.Energy", "Mathlib.SetTheory.Cardinal.Basic", "Mathlib.Data.Bundle", "Mathlib.Data.Finsupp.Pointwise", "Mathlib.Data.Int.AbsoluteValue", "Mathlib.Data.Set.Pointwise.SMul", "Mathlib.Algebra.Symmetrized", "Mathlib.Algebra.Periodic", "Mathlib.Algebra.PUnitInstances", "Mathlib.Algebra.Order.ToIntervalMod", "Mathlib.Algebra.Order.LatticeGroup", "Mathlib.Algebra.Order.Nonneg.Module", "Mathlib.Algebra.Order.Module.Synonym", "Mathlib.Algebra.BigOperators.Finprod", "Mathlib.Algebra.BigOperators.Intervals", "Mathlib.Algebra.Module.Prod", "Mathlib.Algebra.Module.Pi", "Mathlib.Algebra.Module.Projective", "Mathlib.Algebra.Module.BigOperators", "Mathlib.Algebra.Module.Algebra", "Mathlib.Algebra.Module.MinimalAxioms", "Mathlib.Algebra.Ring.AddAut"], "used_by_count": 9}, {"id": "Mathlib.Algebra.Module.Prod", "short_name": "Prod", "kind": "theorem", "module": "Mathlib.Algebra.Module.Prod", "namespace": "Mathlib.Algebra.Module", "doc_string": null, "source_range": null, "deps": ["Mathlib.LinearAlgebra.Basic", "Mathlib.Algebra.Order.Module.OrderedSMul", "Mathlib.Algebra.Star.Prod"], "used_by_count": 2}, {"id": "Mathlib.Algebra.Module.Pi", "short_name": "Pi", "kind": "theorem", "module": "Mathlib.Algebra.Module.Pi", "namespace": "Mathlib.Algebra.Module", "doc_string": null, "source_range": null, "deps": ["Mathlib.Order.Filter.Germ", "Mathlib.Data.Holor", "Mathlib.Data.Matrix.Basic", "Mathlib.Algebra.Order.Module.OrderedSMul", "Mathlib.Algebra.Module.LinearMap", "Mathlib.Algebra.Module.Hom"], "used_by_count": 4}, {"id": "Mathlib.Algebra.Module.MinimalAxioms", "short_name": "MinimalAxioms", "kind": "theorem", "module": "Mathlib.Algebra.Module.MinimalAxioms", "namespace": "Mathlib.Algebra.Module", "doc_string": null, "source_range": null, "deps": ["Mathlib.Topology.ContinuousFunction.Bounded"], "used_by_count": 1}, {"id": "Mathlib.Algebra.Module.PointwisePi", "short_name": "PointwisePi", "kind": "theorem", "module": "Mathlib.Algebra.Module.PointwisePi", "namespace": "Mathlib.Algebra.Module", "doc_string": null, "source_range": null, "deps": [], "used_by_count": 2}, {"id": "Mathlib.Algebra.Module.LinearMap", "short_name": "LinearMap", "kind": "theorem", "module": "Mathlib.Algebra.Module.LinearMap", "namespace": "Mathlib.Algebra.Module", "doc_string": null, "source_range": null, "deps": ["Mathlib.RepresentationTheory.Basic", "Mathlib.CategoryTheory.Linear.Basic", "Mathlib.LinearAlgebra.SesquilinearForm", "Mathlib.Data.DFinsupp.Basic", "Mathlib.Data.ZMod.Module", "Mathlib.Data.Matrix.Basic", "Mathlib.Algebra.Module.Equiv"], "used_by_count": 5}, {"id": "Mathlib.Algebra.Module.Hom", "short_name": "Hom", "kind": "theorem", "module": "Mathlib.Algebra.Module.Hom", "namespace": "Mathlib.Algebra.Module", "doc_string": null, "source_range": null, "deps": ["Mathlib.LinearAlgebra.Basic", "Mathlib.Algebra.Ring.CentroidHom"], "used_by_count": 2}, {"id": "Mathlib.Algebra.Module.Equiv", "short_name": "Equiv", "kind": "theorem", "module": "Mathlib.Algebra.Module.Equiv", "namespace": "Mathlib.Algebra.Module", "doc_string": null, "source_range": null, "deps": ["Mathlib.GroupTheory.FreeAbelianGroupFinsupp", "Mathlib.LinearAlgebra.GeneralLinearGroup", "Mathlib.Data.Finsupp.ToDFinsupp", "Mathlib.Algebra.Module.ULift", "Mathlib.Algebra.Module.Opposites", "Mathlib.Algebra.Module.Submodule.LinearMap", "Mathlib.Algebra.Star.Module"], "used_by_count": 1}, {"id": "Mathlib.Algebra.Module.ULift", "short_name": "ULift", "kind": "theorem", "module": "Mathlib.Algebra.Module.ULift", "namespace": "Mathlib.Algebra.Module", "doc_string": null, "source_range": null, "deps": ["Mathlib.RingTheory.IsTensorProduct", "Mathlib.Algebra.Module.Injective", "Mathlib.Algebra.Algebra.Basic"], "used_by_count": 2}, {"id": "Mathlib.Algebra.Module.Opposites", "short_name": "Opposites", "kind": "theorem", "module": "Mathlib.Algebra.Module.Opposites", "namespace": "Mathlib.Algebra.Module", "doc_string": null, "source_range": null, "deps": ["Mathlib.LinearAlgebra.CliffordAlgebra.Conjugation", "Mathlib.Algebra.Algebra.Opposite", "Mathlib.Algebra.Algebra.Operations"], "used_by_count": 2}, {"id": "Mathlib.Algebra.Module.BigOperators", "short_name": "BigOperators", "kind": "theorem", "module": "Mathlib.Algebra.Module.BigOperators", "namespace": "Mathlib.Algebra.Module", "doc_string": null, "source_range": null, "deps": ["Mathlib.NumberTheory.ArithmeticFunction", "Mathlib.GroupTheory.Perm.Cycle.Basic", "Mathlib.RingTheory.AlgebraTower", "Mathlib.Combinatorics.Pigeonhole", "Mathlib.LinearAlgebra.Dimension", "Mathlib.LinearAlgebra.AffineSpace.Combination", "Mathlib.Algebra.Module.GradedModule", "Mathlib.Algebra.Module.Torsion", "Mathlib.Algebra.MonoidAlgebra.Basic"], "used_by_count": 2}, {"id": "Mathlib.Algebra.Module.Submodule.Basic", "short_name": "Basic", "kind": "theorem", "module": "Mathlib.Algebra.Module.Submodule.Basic", "namespace": "Mathlib.Algebra.Module.Submodule", "doc_string": null, "source_range": null, "deps": ["Mathlib.Order.Filter.ZeroAndBoundedAtFilter", "Mathlib.Analysis.Complex.UpperHalfPlane.FunctionsBoundedAtInfty", "Mathlib.Analysis.Convex.Cone.Pointed", "Mathlib.Algebra.DirectSum.Decomposition", "Mathlib.Algebra.Module.Submodule.LinearMap"], "used_by_count": 2}, {"id": "Mathlib.Algebra.Module.Submodule.LinearMap", "short_name": "LinearMap", "kind": "theorem", "module": "Mathlib.Algebra.Module.Submodule.LinearMap", "namespace": "Mathlib.Algebra.Module.Submodule", "doc_string": null, "source_range": null, "deps": ["Mathlib.Algebra.Module.Submodule.Lattice"], "used_by_count": 2}, {"id": "Mathlib.Algebra.Module.Submodule.Lattice", "short_name": "Lattice", "kind": "theorem", "module": "Mathlib.Algebra.Module.Submodule.Lattice", "namespace": "Mathlib.Algebra.Module.Submodule", "doc_string": null, "source_range": null, "deps": ["Mathlib.Algebra.Module.Submodule.Map"], "used_by_count": 2}, {"id": "Mathlib.Algebra.Module.Submodule.Map", "short_name": "Map", "kind": "theorem", "module": "Mathlib.Algebra.Module.Submodule.Map", "namespace": "Mathlib.Algebra.Module.Submodule", "doc_string": null, "source_range": null, "deps": ["Mathlib.LinearAlgebra.Basic"], "used_by_count": 1}, {"id": "Mathlib.Algebra.Module.Algebra", "short_name": "Algebra", "kind": "theorem", "module": "Mathlib.Algebra.Module.Algebra", "namespace": "Mathlib.Algebra.Module", "doc_string": null, "source_range": null, "deps": ["Mathlib.LinearAlgebra.Matrix.ToLin"], "used_by_count": 2}, {"id": "Mathlib.Algebra.Module.Submodule.Bilinear", "short_name": "Bilinear", "kind": "theorem", "module": "Mathlib.Algebra.Module.Submodule.Bilinear", "namespace": "Mathlib.Algebra.Module.Submodule", "doc_string": null, "source_range": null, "deps": ["Mathlib.LinearAlgebra.TensorProduct", "Mathlib.Algebra.Algebra.Operations"], "used_by_count": 2}, {"id": "Mathlib.Algebra.Module.Submodule.Pointwise", "short_name": "Pointwise", "kind": "theorem", "module": "Mathlib.Algebra.Module.Submodule.Pointwise", "namespace": "Mathlib.Algebra.Module.Submodule", "doc_string": null, "source_range": null, "deps": ["Mathlib.Topology.Algebra.Nonarchimedean.Bases", "Mathlib.Algebra.Algebra.Operations"], "used_by_count": 2}, {"id": "Mathlib.Algebra.Module.Injective", "short_name": "Injective", "kind": "theorem", "module": "Mathlib.Algebra.Module.Injective", "namespace": "Mathlib.Algebra.Module", "doc_string": null, "source_range": null, "deps": ["Mathlib.Algebra.Category.GroupCat.Injective"], "used_by_count": 6}, {"id": "Mathlib.Algebra.Module.Projective", "short_name": "Projective", "kind": "theorem", "module": "Mathlib.Algebra.Module.Projective", "namespace": "Mathlib.Algebra.Module", "doc_string": null, "source_range": null, "deps": ["Mathlib.RingTheory.Flat", "Mathlib.Algebra.Category.ModuleCat.Projective", "Mathlib.Algebra.Module.PID"], "used_by_count": 3}, {"id": "Mathlib.Algebra.Module.GradedModule", "short_name": "GradedModule", "kind": "theorem", "module": "Mathlib.Algebra.Module.GradedModule", "namespace": "Mathlib.Algebra.Module", "doc_string": null, "source_range": null, "deps": [], "used_by_count": 4}, {"id": "Mathlib.Algebra.Module.DirectLimitAndTensorProduct", "short_name": "DirectLimitAndTensorProduct", "kind": "theorem", "module": "Mathlib.Algebra.Module.DirectLimitAndTensorProduct", "namespace": "Mathlib.Algebra.Module", "doc_string": null, "source_range": null, "deps": [], "used_by_count": 1}, {"id": "Mathlib.Algebra.Module.Torsion", "short_name": "Torsion", "kind": "theorem", "module": "Mathlib.Algebra.Module.Torsion", "namespace": "Mathlib.Algebra.Module", "doc_string": null, "source_range": null, "deps": ["Mathlib.RingTheory.Ideal.Cotangent", "Mathlib.LinearAlgebra.Dimension", "Mathlib.Algebra.Module.DedekindDomain"], "used_by_count": 6}, {"id": "Mathlib.Algebra.Module.Bimodule", "short_name": "Bimodule", "kind": "theorem", "module": "Mathlib.Algebra.Module.Bimodule", "namespace": "Mathlib.Algebra.Module", "doc_string": null, "source_range": null, "deps": [], "used_by_count": 1}, {"id": "Mathlib.Algebra.Module.LocalizedModule", "short_name": "LocalizedModule", "kind": "theorem", "module": "Mathlib.Algebra.Module.LocalizedModule", "namespace": "Mathlib.Algebra.Module", "doc_string": null, "source_range": null, "deps": ["Mathlib.AlgebraicGeometry.Spec"], "used_by_count": 5}, {"id": "Mathlib.Algebra.Module.DedekindDomain", "short_name": "DedekindDomain", "kind": "theorem", "module": "Mathlib.Algebra.Module.DedekindDomain", "namespace": "Mathlib.Algebra.Module", "doc_string": null, "source_range": null, "deps": ["Mathlib.Algebra.Module.PID"], "used_by_count": 2}, {"id": "Mathlib.Algebra.Module.PID", "short_name": "PID", "kind": "theorem", "module": "Mathlib.Algebra.Module.PID", "namespace": "Mathlib.Algebra.Module", "doc_string": null, "source_range": null, "deps": ["Mathlib.GroupTheory.FiniteAbelian"], "used_by_count": 4}, {"id": "Mathlib.Algebra.Module.Zlattice", "short_name": "Zlattice", "kind": "theorem", "module": "Mathlib.Algebra.Module.Zlattice", "namespace": "Mathlib.Algebra.Module", "doc_string": null, "source_range": null, "deps": ["Mathlib.NumberTheory.NumberField.CanonicalEmbedding"], "used_by_count": 4}]}