{"nodes": [{"id": "Mathlib.NumberTheory.Zsqrtd.Basic", "short_name": "Basic", "kind": "theorem", "module": "Mathlib.NumberTheory.Zsqrtd.Basic", "namespace": "Mathlib.NumberTheory.Zsqrtd", "doc_string": null, "source_range": null, "deps": ["Mathlib.NumberTheory.Pell", "Mathlib.NumberTheory.PellMatiyasevic", "Mathlib.NumberTheory.Zsqrtd.ToReal", "Mathlib.NumberTheory.Zsqrtd.GaussianInt"], "used_by_count": 4}, {"id": "Mathlib.NumberTheory.Zsqrtd.ToReal", "short_name": "ToReal", "kind": "theorem", "module": "Mathlib.NumberTheory.Zsqrtd.ToReal", "namespace": "Mathlib.NumberTheory.Zsqrtd", "doc_string": null, "source_range": null, "deps": [], "used_by_count": 2}, {"id": "Mathlib.NumberTheory.Zsqrtd.GaussianInt", "short_name": "GaussianInt", "kind": "theorem", "module": "Mathlib.NumberTheory.Zsqrtd.GaussianInt", "namespace": "Mathlib.NumberTheory.Zsqrtd", "doc_string": null, "source_range": null, "deps": ["Mathlib.NumberTheory.Zsqrtd.QuadraticReciprocity"], "used_by_count": 3}, {"id": "Mathlib.NumberTheory.Zsqrtd.QuadraticReciprocity", "short_name": "QuadraticReciprocity", "kind": "theorem", "module": "Mathlib.NumberTheory.Zsqrtd.QuadraticReciprocity", "namespace": "Mathlib.NumberTheory.Zsqrtd", "doc_string": null, "source_range": null, "deps": ["Mathlib.NumberTheory.SumTwoSquares"], "used_by_count": 2}]}